ob_dj_factorial/apis/factorial/__init__.py
ob_dj_factorial/apis/factorial/urls.py
ob_dj_factorial/apis/factorial/views.py
ob_dj_factorial/core/factorial/__init__.py
ob_dj_factorial/core/factorial/apps.py
ob_dj_factorial/core/factorial/managers.py
ob_dj_factorial/core/factorial/models.py
ob_dj_factorial/core/factorial/settings_validation.py
ob_dj_factorial/core/factorial/tasks.py
ob_dj_factorial/core/factorial/urls.py
ob_dj_factorial/core/factorial/utils.py
ob_dj_factorial/core/factorial/views.py
ob_dj_factorial/core/factorial/admin/__init__.py
ob_dj_factorial/core/factorial/migrations/0001_initial.py
ob_dj_factorial/core/factorial/migrations/0002_fhemployee_email.py
ob_dj_factorial/core/factorial/migrations/__init__.py
ob_dj_factorial/core/factorial/templates/admin_oauth_change_list.html
ob_dj_factorial-0.0.2.dist-info/METADATA
ob_dj_factorial-0.0.2.dist-info/WHEEL
ob_dj_factorial-0.0.2.dist-info/top_level.txt
ob_dj_factorial-0.0.2.dist-info/RECORD
