Metadata-Version: 2.1
Name: ob-dj-factorial
Version: 0.0.2
Summary: OBytes django application for managing FactorialHR integration and sync data from and to FactorialHR.
Home-page: https://www.obytes.com/
Author: OBytes
Author-email: hello@obytes.com
License: BSD-3-Clause
Platform: UNKNOWN
Classifier: Environment :: Web Environment
Classifier: Framework :: Django
Classifier: Intended Audience :: Developers
Classifier: License :: OSI Approved :: BSD License
Classifier: Operating System :: OS Independent
Classifier: Programming Language :: Python
Classifier: Programming Language :: Python :: 3
Classifier: Programming Language :: Python :: 3 :: Only
Classifier: Programming Language :: Python :: 3.8
Classifier: Topic :: Internet :: WWW/HTTP
Classifier: Topic :: Internet :: WWW/HTTP :: Dynamic Content
Requires-Python: >=3.8
Requires-Dist: django
Requires-Dist: celery
Requires-Dist: djangorestframework
